infernite/__init__.py
infernite/infernite.py
infernite-0.0.1.dist-info/METADATA
infernite-0.0.1.dist-info/WHEEL
infernite-0.0.1.dist-info/top_level.txt
infernite-0.0.1.dist-info/RECORD
